{"premise": "Tan dog running through long grass in a park-like setting.", "hypothesis": "A dog runs after a squirrel.", "label": 1}
{"premise": "Tan dog running through long grass in a park-like setting.", "hypothesis": "A dog runs after a squirrel.", "label": 1}
{"premise": "The man in the white shirt holds up a playing card.", "hypothesis": "The man is holding up the Ace of Spades.", "label": 1}
{"premise": "Violin soloists take the stage during the orchestra's opening show at the theater.", "hypothesis": "People are playing the harmonica while standing on a roof.", "label": 0}
{"premise": "A man in an orange hat holds a ball.", "hypothesis": "A man in a blue hat drops the ball.", "label": 0}
{"premise": "A man with a light blue t-shirt outside in the open wearing red ear protection while firing a gun.", "hypothesis": "A man is signaling the start of a race.", "label": 1}
{"premise": "A man with a tattoo on his arm staring to the side with vehicles and buildings behind him.", "hypothesis": "A man is standing outside near a street.", "label": -1}
{"premise": "Two men in costumes with fake carrot noses, top hats, sunglasses and white fur coats that contain white electrical lights.", "hypothesis": "Nobody has a costume one", "label": 0}
{"premise": "Children are playing in the street with a toy.", "hypothesis": "The children have a ball.", "label": 1}
{"premise": "People sitting in chairs along a tree-lined sidewalk.", "hypothesis": "People are watching the flowers blossom", "label": 1}
{"premise": "Two street people and a dog sitting on the ground and one is holding an \"out of luck\" sign.", "hypothesis": "the people are swimming in the red sea", "label": -1}
{"premise": "In a snowy residential environment, a man with a brown jacket and gray mustache and beard places a hand on a felled log while another man in a blue shirt is blurry on the right side of the photo.", "hypothesis": "The men have put out a fire.", "label": 0}
{"premise": "A man in a black shirt working on a guitar.", "hypothesis": "A guy working on his instrument.", "label": 2}
{"premise": "A man reads the paper in a bar with green lighting.", "hypothesis": "The man is reading the sportspage.", "label": 1}
{"premise": "A boy rollerskating in the street.", "hypothesis": "A boy is sleeping", "label": 0}
{"premise": "A group of adults standing up with children in sports attire kneeling on the ground.", "hypothesis": "A group of adults and kids.", "label": 2}
{"premise": "A black man in a knitted, blue cap and green, collared shirt sit next to a stump slicing a coconut.", "hypothesis": "A man drinking coconut water.", "label": 0}
{"premise": "A man standing in a cubicle with a chair that has a black Ginobili jersey on it.", "hypothesis": "A man is wearing a white sport jersey in his cubicle.", "label": 0}
{"premise": "A woman, wearing a colorful bikini, rests laying down next to the blue water.", "hypothesis": "The woman is wearing a prom dress.", "label": 0}
{"premise": "Topless girl riding a red bike.", "hypothesis": "A woman is on a bike.", "label": 2}
{"premise": "3 ladies with numbers on their shirts running.", "hypothesis": "The ladies are riding bikes.", "label": 0}
